uspeedo/__init__.py
uspeedo/client.py
uspeedo/version.py
uspeedo/core/__init__.py
uspeedo/core/auth/__init__.py
uspeedo/core/auth/_cfg.py
uspeedo/core/client/__init__.py
uspeedo/core/client/_cfg.py
uspeedo/core/client/_client.py
uspeedo/core/exc/__init__.py
uspeedo/core/exc/_exc.py
uspeedo/core/transport/__init__.py
uspeedo/core/transport/_requests.py
uspeedo/core/transport/http.py
uspeedo/core/transport/utils.py
uspeedo/core/typesystem/__init__.py
uspeedo/core/typesystem/abstract.py
uspeedo/core/typesystem/encoder.py
uspeedo/core/typesystem/fields.py
uspeedo/core/typesystem/schema.py
uspeedo/core/utils/__init__.py
uspeedo/core/utils/compat.py
uspeedo/core/utils/deco.py
uspeedo/core/utils/log.py
uspeedo/core/utils/middleware.py
uspeedo/helpers/__init__.py
uspeedo/helpers/utils.py
uspeedo/helpers/wait.py
uspeedo/services/__init__.py
uspeedo/services/asms/__init__.py
uspeedo/services/asms/client.py
uspeedo/services/asms/apis/CreateUSMSTemplateReq.py
uspeedo/services/asms/apis/CreateUSMSTemplateResp.py
uspeedo/services/asms/apis/DeleteUSMSTemplateReq.py
uspeedo/services/asms/apis/DeleteUSMSTemplateResp.py
uspeedo/services/asms/apis/GetUSMSSendReceiptReq.py
uspeedo/services/asms/apis/GetUSMSSendReceiptResp.py
uspeedo/services/asms/apis/QueryUSMSTemplateReq.py
uspeedo/services/asms/apis/QueryUSMSTemplateResp.py
uspeedo/services/asms/apis/SendBatchUSMSMessageReq.py
uspeedo/services/asms/apis/SendBatchUSMSMessageResp.py
uspeedo/services/asms/apis/UpdateUSMSTemplateReq.py
uspeedo/services/asms/apis/UpdateUSMSTemplateResp.py
uspeedo/services/asms/apis/__init__.py
uspeedo/services/asms/models/OutTemplate.py
uspeedo/services/asms/models/ReceiptPerPhone.py
uspeedo/services/asms/models/ReceiptPerSession.py
uspeedo/services/asms/models/SendInfo.py
uspeedo/services/asms/models/SendInfoWithFailure.py
uspeedo/services/asms/models/TargetPhone.py
uspeedo/services/asms/models/TargetPhoneWithFailure.py
uspeedo/services/asms/models/VariableAttr.py
uspeedo_sdk_python-1.5.0.dist-info/LICENSE
uspeedo_sdk_python-1.5.0.dist-info/METADATA
uspeedo_sdk_python-1.5.0.dist-info/WHEEL
uspeedo_sdk_python-1.5.0.dist-info/top_level.txt
uspeedo_sdk_python-1.5.0.dist-info/RECORD
